{
    "FullTypeName":  "Microsoft.Dynamics.AX.Metadata.MetaModel.AxQueryExtensionQueryDataSourceRange",
    "Assembly":  "Microsoft.Dynamics.AX.Metadata",
    "ObjectName":  "AxQueryExtensionQueryDataSourceRange",
    "DiscoveryDate":  "2025-08-28T23:16:59",
    "Namespace":  "Microsoft.Dynamics.AX.Metadata.MetaModel",
    "Categories":  {
                       "Flags":  [

                                 ],
                       "Code":  [
                                    {
                                        "FullType":  "Microsoft.Dynamics.AX.Metadata.MetaModel.AxQuerySimpleDataSourceRange",
                                        "CanWrite":  true,
                                        "Type":  "AxQuerySimpleDataSourceRange",
                                        "CanRead":  true,
                                        "Category":  "Code",
                                        "IsEnum":  false,
                                        "EnumValues":  [

                                                       ],
                                        "Name":  "QueryDataSourceRange",
                                        "IsCollection":  false
                                    }
                                ],
                       "Identity":  [
                                        {
                                            "FullType":  "System.String",
                                            "CanWrite":  true,
                                            "Type":  "String",
                                            "CanRead":  true,
                                            "Category":  "Identity",
                                            "IsEnum":  false,
                                            "EnumValues":  [

                                                           ],
                                            "Name":  "Name",
                                            "IsCollection":  false
                                        }
                                    ],
                       "Other":  [
                                     {
                                         "FullType":  "System.String",
                                         "CanWrite":  true,
                                         "Type":  "String",
                                         "CanRead":  true,
                                         "Category":  "Other",
                                         "IsEnum":  false,
                                         "EnumValues":  [

                                                        ],
                                         "Name":  "Tags",
                                         "IsCollection":  false
                                     },
                                     {
                                         "FullType":  "System.String",
                                         "CanWrite":  true,
                                         "Type":  "String",
                                         "CanRead":  true,
                                         "Category":  "Other",
                                         "IsEnum":  false,
                                         "EnumValues":  [

                                                        ],
                                         "Name":  "Parent",
                                         "IsCollection":  false
                                     }
                                 ],
                       "Metadata":  [

                                    ],
                       "Enums":  [

                                 ],
                       "Collections":  [

                                       ]
                   },
    "AllProperties":  [
                          {
                              "FullType":  "System.String",
                              "CanWrite":  true,
                              "Type":  "String",
                              "CanRead":  true,
                              "Category":  "Other",
                              "IsEnum":  false,
                              "EnumValues":  [

                                             ],
                              "Name":  "Tags",
                              "IsCollection":  false
                          },
                          {
                              "FullType":  "System.String",
                              "CanWrite":  true,
                              "Type":  "String",
                              "CanRead":  true,
                              "Category":  "Other",
                              "IsEnum":  false,
                              "EnumValues":  [

                                             ],
                              "Name":  "Parent",
                              "IsCollection":  false
                          },
                          {
                              "FullType":  "Microsoft.Dynamics.AX.Metadata.MetaModel.AxQuerySimpleDataSourceRange",
                              "CanWrite":  true,
                              "Type":  "AxQuerySimpleDataSourceRange",
                              "CanRead":  true,
                              "Category":  "Code",
                              "IsEnum":  false,
                              "EnumValues":  [

                                             ],
                              "Name":  "QueryDataSourceRange",
                              "IsCollection":  false
                          },
                          {
                              "FullType":  "System.String",
                              "CanWrite":  true,
                              "Type":  "String",
                              "CanRead":  true,
                              "Category":  "Identity",
                              "IsEnum":  false,
                              "EnumValues":  [

                                             ],
                              "Name":  "Name",
                              "IsCollection":  false
                          }
                      ],
    "PropertyCount":  4
}