{
    "FullTypeName":  "Microsoft.Dynamics.AX.Metadata.MetaModel.AxWorkflowElementReference",
    "Assembly":  "Microsoft.Dynamics.AX.Metadata",
    "ObjectName":  "AxWorkflowElementReference",
    "DiscoveryDate":  "2025-08-28T23:17:04",
    "Namespace":  "Microsoft.Dynamics.AX.Metadata.MetaModel",
    "Categories":  {
                       "Flags":  [

                                 ],
                       "Code":  [

                                ],
                       "Identity":  [
                                        {
                                            "FullType":  "System.String",
                                            "CanWrite":  true,
                                            "Type":  "String",
                                            "CanRead":  true,
                                            "Category":  "Identity",
                                            "IsEnum":  false,
                                            "EnumValues":  [

                                                           ],
                                            "Name":  "Name",
                                            "IsCollection":  false
                                        }
                                    ],
                       "Other":  [
                                     {
                                         "FullType":  "System.String",
                                         "CanWrite":  true,
                                         "Type":  "String",
                                         "CanRead":  true,
                                         "Category":  "Other",
                                         "IsEnum":  false,
                                         "EnumValues":  [

                                                        ],
                                         "Name":  "Tags",
                                         "IsCollection":  false
                                     },
                                     {
                                         "FullType":  "System.String",
                                         "CanWrite":  true,
                                         "Type":  "String",
                                         "CanRead":  true,
                                         "Category":  "Other",
                                         "IsEnum":  false,
                                         "EnumValues":  [

                                                        ],
                                         "Name":  "ElementName",
                                         "IsCollection":  false
                                     }
                                 ],
                       "Metadata":  [

                                    ],
                       "Enums":  [
                                     {
                                         "FullType":  "Microsoft.Dynamics.AX.Metadata.Core.MetaModel.WorkflowElementType",
                                         "CanWrite":  true,
                                         "Type":  "WorkflowElementType",
                                         "CanRead":  true,
                                         "Category":  "Enum",
                                         "IsEnum":  true,
                                         "EnumValues":  [
                                                            "Approval",
                                                            "Task",
                                                            "SubWorkflow",
                                                            "AutomatedTask",
                                                            "ConditionalGateway",
                                                            "Start",
                                                            "End",
                                                            "ManualGateway",
                                                            "Parallel",
                                                            "ParallelBranch",
                                                            "LineItemWorkflow"
                                                        ],
                                         "Name":  "Type",
                                         "IsCollection":  false
                                     }
                                 ],
                       "Collections":  [

                                       ]
                   },
    "AllProperties":  [
                          {
                              "FullType":  "System.String",
                              "CanWrite":  true,
                              "Type":  "String",
                              "CanRead":  true,
                              "Category":  "Identity",
                              "IsEnum":  false,
                              "EnumValues":  [

                                             ],
                              "Name":  "Name",
                              "IsCollection":  false
                          },
                          {
                              "FullType":  "System.String",
                              "CanWrite":  true,
                              "Type":  "String",
                              "CanRead":  true,
                              "Category":  "Other",
                              "IsEnum":  false,
                              "EnumValues":  [

                                             ],
                              "Name":  "Tags",
                              "IsCollection":  false
                          },
                          {
                              "FullType":  "System.String",
                              "CanWrite":  true,
                              "Type":  "String",
                              "CanRead":  true,
                              "Category":  "Other",
                              "IsEnum":  false,
                              "EnumValues":  [

                                             ],
                              "Name":  "ElementName",
                              "IsCollection":  false
                          },
                          {
                              "FullType":  "Microsoft.Dynamics.AX.Metadata.Core.MetaModel.WorkflowElementType",
                              "CanWrite":  true,
                              "Type":  "WorkflowElementType",
                              "CanRead":  true,
                              "Category":  "Enum",
                              "IsEnum":  true,
                              "EnumValues":  [
                                                 "Approval",
                                                 "Task",
                                                 "SubWorkflow",
                                                 "AutomatedTask",
                                                 "ConditionalGateway",
                                                 "Start",
                                                 "End",
                                                 "ManualGateway",
                                                 "Parallel",
                                                 "ParallelBranch",
                                                 "LineItemWorkflow"
                                             ],
                              "Name":  "Type",
                              "IsCollection":  false
                          }
                      ],
    "PropertyCount":  4
}